<?xml version="1.0" encoding="UTF-8" ?>
<!DOCTYPE characterMapping SYSTEM "http://www.unicode.org/unicode/reports/tr22/CharacterMapping.dtd">
<characterMapping id="windows-1140-2000" version="1">
 <history>
  <modified version="1" date="2001-04-18">This file was generated with XMLSimpleGenerator.java.</modified>
 </history>
 <validity>
  <state type="FIRST" next="VALID" s="00" e="FF" max="FFFF"/>
 </validity>
 <assignments sub="6F">
  <!-- One to one mappings -->
  <a u="0000" b="00"/>
  <a u="0001" b="01"/>
  <a u="0002" b="02"/>
  <a u="0003" b="03"/>
  <a u="0004" b="37"/>
  <a u="0005" b="2D"/>
  <a u="0006" b="2E"/>
  <a u="0007" b="2F"/>
  <a u="0008" b="16"/>
  <a u="0009" b="05"/>
  <a u="000A" b="25"/>
  <a u="000B" b="0B"/>
  <a u="000C" b="0C"/>
  <a u="000D" b="0D"/>
  <a u="000E" b="0E"/>
  <a u="000F" b="0F"/>
  <a u="0010" b="10"/>
  <a u="0011" b="11"/>
  <a u="0012" b="12"/>
  <a u="0013" b="13"/>
  <a u="0014" b="3C"/>
  <a u="0015" b="3D"/>
  <a u="0016" b="32"/>
  <a u="0017" b="26"/>
  <a u="0018" b="18"/>
  <a u="0019" b="19"/>
  <a u="001A" b="3F"/>
  <a u="001B" b="27"/>
  <a u="001C" b="1C"/>
  <a u="001D" b="1D"/>
  <a u="001E" b="1E"/>
  <a u="001F" b="1F"/>
  <a u="0020" b="40"/>
  <a u="0021" b="5A"/>
  <a u="0022" b="7F"/>
  <a u="0023" b="7B"/>
  <a u="0024" b="5B"/>
  <a u="0025" b="6C"/>
  <a u="0026" b="50"/>
  <a u="0027" b="7D"/>
  <a u="0028" b="4D"/>
  <a u="0029" b="5D"/>
  <a u="002A" b="5C"/>
  <a u="002B" b="4E"/>
  <a u="002C" b="6B"/>
  <a u="002D" b="60"/>
  <a u="002E" b="4B"/>
  <a u="002F" b="61"/>
  <a u="0030" b="F0"/>
  <a u="0031" b="F1"/>
  <a u="0032" b="F2"/>
  <a u="0033" b="F3"/>
  <a u="0034" b="F4"/>
  <a u="0035" b="F5"/>
  <a u="0036" b="F6"/>
  <a u="0037" b="F7"/>
  <a u="0038" b="F8"/>
  <a u="0039" b="F9"/>
  <a u="003A" b="7A"/>
  <a u="003B" b="5E"/>
  <a u="003C" b="4C"/>
  <a u="003D" b="7E"/>
  <a u="003E" b="6E"/>
  <a u="003F" b="6F"/>
  <a u="0040" b="7C"/>
  <a u="0041" b="C1"/>
  <a u="0042" b="C2"/>
  <a u="0043" b="C3"/>
  <a u="0044" b="C4"/>
  <a u="0045" b="C5"/>
  <a u="0046" b="C6"/>
  <a u="0047" b="C7"/>
  <a u="0048" b="C8"/>
  <a u="0049" b="C9"/>
  <a u="004A" b="D1"/>
  <a u="004B" b="D2"/>
  <a u="004C" b="D3"/>
  <a u="004D" b="D4"/>
  <a u="004E" b="D5"/>
  <a u="004F" b="D6"/>
  <a u="0050" b="D7"/>
  <a u="0051" b="D8"/>
  <a u="0052" b="D9"/>
  <a u="0053" b="E2"/>
  <a u="0054" b="E3"/>
  <a u="0055" b="E4"/>
  <a u="0056" b="E5"/>
  <a u="0057" b="E6"/>
  <a u="0058" b="E7"/>
  <a u="0059" b="E8"/>
  <a u="005A" b="E9"/>
  <a u="005B" b="BA"/>
  <a u="005C" b="E0"/>
  <a u="005D" b="BB"/>
  <a u="005E" b="B0"/>
  <a u="005F" b="6D"/>
  <a u="0060" b="79"/>
  <a u="0061" b="81"/>
  <a u="0062" b="82"/>
  <a u="0063" b="83"/>
  <a u="0064" b="84"/>
  <a u="0065" b="85"/>
  <a u="0066" b="86"/>
  <a u="0067" b="87"/>
  <a u="0068" b="88"/>
  <a u="0069" b="89"/>
  <a u="006A" b="91"/>
  <a u="006B" b="92"/>
  <a u="006C" b="93"/>
  <a u="006D" b="94"/>
  <a u="006E" b="95"/>
  <a u="006F" b="96"/>
  <a u="0070" b="97"/>
  <a u="0071" b="98"/>
  <a u="0072" b="99"/>
  <a u="0073" b="A2"/>
  <a u="0074" b="A3"/>
  <a u="0075" b="A4"/>
  <a u="0076" b="A5"/>
  <a u="0077" b="A6"/>
  <a u="0078" b="A7"/>
  <a u="0079" b="A8"/>
  <a u="007A" b="A9"/>
  <a u="007B" b="C0"/>
  <a u="007C" b="4F"/>
  <a u="007D" b="D0"/>
  <a u="007E" b="A1"/>
  <a u="007F" b="07"/>
  <a u="0080" b="20"/>
  <a u="0081" b="21"/>
  <a u="0082" b="22"/>
  <a u="0083" b="23"/>
  <a u="0084" b="24"/>
  <a u="0085" b="15"/>
  <a u="0086" b="06"/>
  <a u="0087" b="17"/>
  <a u="0088" b="28"/>
  <a u="0089" b="29"/>
  <a u="008A" b="2A"/>
  <a u="008B" b="2B"/>
  <a u="008C" b="2C"/>
  <a u="008D" b="09"/>
  <a u="008E" b="0A"/>
  <a u="008F" b="1B"/>
  <a u="0090" b="30"/>
  <a u="0091" b="31"/>
  <a u="0092" b="1A"/>
  <a u="0093" b="33"/>
  <a u="0094" b="34"/>
  <a u="0095" b="35"/>
  <a u="0096" b="36"/>
  <a u="0097" b="08"/>
  <a u="0098" b="38"/>
  <a u="0099" b="39"/>
  <a u="009A" b="3A"/>
  <a u="009B" b="3B"/>
  <a u="009C" b="04"/>
  <a u="009D" b="14"/>
  <a u="009E" b="3E"/>
  <a u="009F" b="FF"/>
  <a u="00A0" b="41"/>
  <a u="00A1" b="AA"/>
  <a u="00A2" b="4A"/>
  <a u="00A3" b="B1"/>
  <a u="00A5" b="B2"/>
  <a u="00A6" b="6A"/>
  <a u="00A7" b="B5"/>
  <a u="00A8" b="BD"/>
  <a u="00A9" b="B4"/>
  <a u="00AA" b="9A"/>
  <a u="00AB" b="8A"/>
  <a u="00AC" b="5F"/>
  <a u="00AD" b="CA"/>
  <a u="00AE" b="AF"/>
  <a u="00AF" b="BC"/>
  <a u="00B0" b="90"/>
  <a u="00B1" b="8F"/>
  <a u="00B2" b="EA"/>
  <a u="00B3" b="FA"/>
  <a u="00B4" b="BE"/>
  <a u="00B5" b="A0"/>
  <a u="00B6" b="B6"/>
  <a u="00B7" b="B3"/>
  <a u="00B8" b="9D"/>
  <a u="00B9" b="DA"/>
  <a u="00BA" b="9B"/>
  <a u="00BB" b="8B"/>
  <a u="00BC" b="B7"/>
  <a u="00BD" b="B8"/>
  <a u="00BE" b="B9"/>
  <a u="00BF" b="AB"/>
  <a u="00C0" b="64"/>
  <a u="00C1" b="65"/>
  <a u="00C2" b="62"/>
  <a u="00C3" b="66"/>
  <a u="00C4" b="63"/>
  <a u="00C5" b="67"/>
  <a u="00C6" b="9E"/>
  <a u="00C7" b="68"/>
  <a u="00C8" b="74"/>
  <a u="00C9" b="71"/>
  <a u="00CA" b="72"/>
  <a u="00CB" b="73"/>
  <a u="00CC" b="78"/>
  <a u="00CD" b="75"/>
  <a u="00CE" b="76"/>
  <a u="00CF" b="77"/>
  <a u="00D0" b="AC"/>
  <a u="00D1" b="69"/>
  <a u="00D2" b="ED"/>
  <a u="00D3" b="EE"/>
  <a u="00D4" b="EB"/>
  <a u="00D5" b="EF"/>
  <a u="00D6" b="EC"/>
  <a u="00D7" b="BF"/>
  <a u="00D8" b="80"/>
  <a u="00D9" b="FD"/>
  <a u="00DA" b="FE"/>
  <a u="00DB" b="FB"/>
  <a u="00DC" b="FC"/>
  <a u="00DD" b="AD"/>
  <a u="00DE" b="AE"/>
  <a u="00DF" b="59"/>
  <a u="00E0" b="44"/>
  <a u="00E1" b="45"/>
  <a u="00E2" b="42"/>
  <a u="00E3" b="46"/>
  <a u="00E4" b="43"/>
  <a u="00E5" b="47"/>
  <a u="00E6" b="9C"/>
  <a u="00E7" b="48"/>
  <a u="00E8" b="54"/>
  <a u="00E9" b="51"/>
  <a u="00EA" b="52"/>
  <a u="00EB" b="53"/>
  <a u="00EC" b="58"/>
  <a u="00ED" b="55"/>
  <a u="00EE" b="56"/>
  <a u="00EF" b="57"/>
  <a u="00F0" b="8C"/>
  <a u="00F1" b="49"/>
  <a u="00F2" b="CD"/>
  <a u="00F3" b="CE"/>
  <a u="00F4" b="CB"/>
  <a u="00F5" b="CF"/>
  <a u="00F6" b="CC"/>
  <a u="00F7" b="E1"/>
  <a u="00F8" b="70"/>
  <a u="00F9" b="DD"/>
  <a u="00FA" b="DE"/>
  <a u="00FB" b="DB"/>
  <a u="00FC" b="DC"/>
  <a u="00FD" b="8D"/>
  <a u="00FE" b="8E"/>
  <a u="00FF" b="DF"/>
  <a u="20AC" b="9F"/>
  <!-- Fallback mappings from Unicode to bytes -->
  <fub u="0178" b="E8"/>
  <fub u="203E" b="BC"/>
  <fub u="FF01" b="5A"/>
  <fub u="FF02" b="7F"/>
  <fub u="FF03" b="7B"/>
  <fub u="FF04" b="5B"/>
  <fub u="FF05" b="6C"/>
  <fub u="FF06" b="50"/>
  <fub u="FF07" b="7D"/>
  <fub u="FF08" b="4D"/>
  <fub u="FF09" b="5D"/>
  <fub u="FF0A" b="5C"/>
  <fub u="FF0B" b="4E"/>
  <fub u="FF0C" b="6B"/>
  <fub u="FF0D" b="60"/>
  <fub u="FF0E" b="4B"/>
  <fub u="FF0F" b="61"/>
  <fub u="FF10" b="F0"/>
  <fub u="FF11" b="F1"/>
  <fub u="FF12" b="F2"/>
  <fub u="FF13" b="F3"/>
  <fub u="FF14" b="F4"/>
  <fub u="FF15" b="F5"/>
  <fub u="FF16" b="F6"/>
  <fub u="FF17" b="F7"/>
  <fub u="FF18" b="F8"/>
  <fub u="FF19" b="F9"/>
  <fub u="FF1A" b="7A"/>
  <fub u="FF1B" b="5E"/>
  <fub u="FF1C" b="4C"/>
  <fub u="FF1D" b="7E"/>
  <fub u="FF1E" b="6E"/>
  <fub u="FF20" b="7C"/>
  <fub u="FF21" b="C1"/>
  <fub u="FF22" b="C2"/>
  <fub u="FF23" b="C3"/>
  <fub u="FF24" b="C4"/>
  <fub u="FF25" b="C5"/>
  <fub u="FF26" b="C6"/>
  <fub u="FF27" b="C7"/>
  <fub u="FF28" b="C8"/>
  <fub u="FF29" b="C9"/>
  <fub u="FF2A" b="D1"/>
  <fub u="FF2B" b="D2"/>
  <fub u="FF2C" b="D3"/>
  <fub u="FF2D" b="D4"/>
  <fub u="FF2E" b="D5"/>
  <fub u="FF2F" b="D6"/>
  <fub u="FF30" b="D7"/>
  <fub u="FF31" b="D8"/>
  <fub u="FF32" b="D9"/>
  <fub u="FF33" b="E2"/>
  <fub u="FF34" b="E3"/>
  <fub u="FF35" b="E4"/>
  <fub u="FF36" b="E5"/>
  <fub u="FF37" b="E6"/>
  <fub u="FF38" b="E7"/>
  <fub u="FF39" b="E8"/>
  <fub u="FF3A" b="E9"/>
  <fub u="FF3B" b="BA"/>
  <fub u="FF3C" b="E0"/>
  <fub u="FF3D" b="BB"/>
  <fub u="FF3E" b="B0"/>
  <fub u="FF3F" b="6D"/>
  <fub u="FF40" b="79"/>
  <fub u="FF41" b="81"/>
  <fub u="FF42" b="82"/>
  <fub u="FF43" b="83"/>
  <fub u="FF44" b="84"/>
  <fub u="FF45" b="85"/>
  <fub u="FF46" b="86"/>
  <fub u="FF47" b="87"/>
  <fub u="FF48" b="88"/>
  <fub u="FF49" b="89"/>
  <fub u="FF4A" b="91"/>
  <fub u="FF4B" b="92"/>
  <fub u="FF4C" b="93"/>
  <fub u="FF4D" b="94"/>
  <fub u="FF4E" b="95"/>
  <fub u="FF4F" b="96"/>
  <fub u="FF50" b="97"/>
  <fub u="FF51" b="98"/>
  <fub u="FF52" b="99"/>
  <fub u="FF53" b="A2"/>
  <fub u="FF54" b="A3"/>
  <fub u="FF55" b="A4"/>
  <fub u="FF56" b="A5"/>
  <fub u="FF57" b="A6"/>
  <fub u="FF58" b="A7"/>
  <fub u="FF59" b="A8"/>
  <fub u="FF5A" b="A9"/>
  <fub u="FF5B" b="C0"/>
  <fub u="FF5C" b="4F"/>
  <fub u="FF5D" b="D0"/>
  <fub u="FF5E" b="A1"/>
  <!-- Fallback mappings from bytes to Unicode -->
  <!-- NONE -->
 </assignments>
</characterMapping>
